{
    "playerstats": {
        "steamID": "76561198131650587",
        "gameName": "ValveTestApp260",
        "stats": [
            {
                "name": "total_kills",
                "value": 49
            },
            {
                "name": "total_deaths",
                "value": 83
            },
            {
                "name": "total_time_played",
                "value": 5933
            },
            {
                "name": "total_planted_bombs",
                "value": 1
            },
            {
                "name": "total_wins",
                "value": 28
            },
            {
                "name": "total_damage_done",
                "value": 6599
            },
            {
                "name": "total_money_earned",
                "value": 130050
            },
            {
                "name": "total_kills_glock",
                "value": 3
            },
            {
                "name": "total_kills_deagle",
                "value": 2
            },
            {
                "name": "total_kills_elite",
                "value": 1
            },
            {
                "name": "total_kills_xm1014",
                "value": 1
            },
            {
                "name": "total_kills_ump45",
                "value": 6
            },
            {
                "name": "total_kills_p90",
                "value": 12
            },
            {
                "name": "total_kills_awp",
                "value": 9
            },
            {
                "name": "total_kills_ak47",
                "value": 3
            },
            {
                "name": "total_kills_famas",
                "value": 4
            },
            {
                "name": "total_kills_g3sg1",
                "value": 1
            },
            {
                "name": "total_kills_headshot",
                "value": 19
            },
            {
                "name": "total_kills_enemy_weapon",
                "value": 3
            },
            {
                "name": "total_wins_map_de_dust2",
                "value": 28
            },
            {
                "name": "total_weapons_donated",
                "value": 2
            },
            {
                "name": "total_kills_against_zoomed_sniper",
                "value": 5
            },
            {
                "name": "total_revenges",
                "value": 1
            },
            {
                "name": "total_shots_hit",
                "value": 204
            },
            {
                "name": "total_shots_fired",
                "value": 2089
            },
            {
                "name": "total_rounds_played",
                "value": 52
            },
            {
                "name": "total_shots_deagle",
                "value": 35
            },
            {
                "name": "total_shots_glock",
                "value": 77
            },
            {
                "name": "total_shots_elite",
                "value": 55
            },
            {
                "name": "total_shots_awp",
                "value": 44
            },
            {
                "name": "total_shots_ak47",
                "value": 180
            },
            {
                "name": "total_shots_aug",
                "value": 39
            },
            {
                "name": "total_shots_famas",
                "value": 74
            },
            {
                "name": "total_shots_g3sg1",
                "value": 20
            },
            {
                "name": "total_shots_p90",
                "value": 970
            },
            {
                "name": "total_shots_ump45",
                "value": 156
            },
            {
                "name": "total_shots_xm1014",
                "value": 42
            },
            {
                "name": "total_shots_m249",
                "value": 32
            },
            {
                "name": "total_hits_deagle",
                "value": 9
            },
            {
                "name": "total_hits_glock",
                "value": 7
            },
            {
                "name": "total_hits_elite",
                "value": 3
            },
            {
                "name": "total_hits_awp",
                "value": 10
            },
            {
                "name": "total_hits_ak47",
                "value": 16
            },
            {
                "name": "total_hits_aug",
                "value": 4
            },
            {
                "name": "total_hits_famas",
                "value": 9
            },
            {
                "name": "total_hits_g3sg1",
                "value": 3
            },
            {
                "name": "total_hits_p90",
                "value": 83
            },
            {
                "name": "total_hits_ump45",
                "value": 12
            },
            {
                "name": "total_hits_xm1014",
                "value": 6
            },
            {
                "name": "total_rounds_map_de_dust2",
                "value": 52
            },
            {
                "name": "last_match_t_wins",
                "value": 1
            },
            {
                "name": "last_match_ct_wins",
                "value": 0
            },
            {
                "name": "last_match_wins",
                "value": 0
            },
            {
                "name": "last_match_max_players",
                "value": 16
            },
            {
                "name": "last_match_kills",
                "value": 12
            },
            {
                "name": "last_match_deaths",
                "value": 30
            },
            {
                "name": "last_match_mvps",
                "value": 0
            },
            {
                "name": "last_match_favweapon_id",
                "value": 19
            },
            {
                "name": "last_match_favweapon_shots",
                "value": 360
            },
            {
                "name": "last_match_favweapon_hits",
                "value": 22
            },
            {
                "name": "last_match_favweapon_kills",
                "value": 4
            },
            {
                "name": "last_match_damage",
                "value": 1194
            },
            {
                "name": "last_match_money_spent",
                "value": 91700
            },
            {
                "name": "last_match_revenges",
                "value": 1
            },
            {
                "name": "total_mvps",
                "value": 1
            },
            {
                "name": "total_gun_game_rounds_played",
                "value": 1
            },
            {
                "name": "total_matches_won",
                "value": 2
            },
            {
                "name": "total_matches_played",
                "value": 5
            },
            {
                "name": "total_gg_matches_played",
                "value": 1
            },
            {
                "name": "total_contribution_score",
                "value": 208
            },
            {
                "name": "last_match_contribution_score",
                "value": 151
            },
            {
                "name": "last_match_rounds",
                "value": 1
            },
            {
                "name": "total_kills_hkp2000",
                "value": 1
            },
            {
                "name": "total_shots_hkp2000",
                "value": 12
            },
            {
                "name": "total_hits_hkp2000",
                "value": 1
            },
            {
                "name": "total_shots_sg556",
                "value": 39
            },
            {
                "name": "total_shots_ssg08",
                "value": 1
            },
            {
                "name": "total_shots_mp7",
                "value": 76
            },
            {
                "name": "total_hits_mp7",
                "value": 2
            },
            {
                "name": "total_hits_nova",
                "value": 14
            },
            {
                "name": "total_kills_nova",
                "value": 1
            },
            {
                "name": "total_shots_nova",
                "value": 63
            },
            {
                "name": "total_shots_bizon",
                "value": 48
            },
            {
                "name": "total_hits_bizon",
                "value": 3
            },
            {
                "name": "total_kills_m4a1",
                "value": 4
            },
            {
                "name": "total_kills_galilar",
                "value": 1
            },
            {
                "name": "total_shots_m4a1",
                "value": 103
            },
            {
                "name": "total_shots_galilar",
                "value": 23
            },
            {
                "name": "total_hits_m4a1",
                "value": 15
            },
            {
                "name": "total_hits_galilar",
                "value": 7
            },
            {
                "name": "GI.lesson.csgo_instr_explain_buymenu",
                "value": 16
            },
            {
                "name": "GI.lesson.csgo_instr_explain_plant_bomb",
                "value": 16
            },
            {
                "name": "GI.lesson.csgo_instr_explain_bomb_carrier",
                "value": 1
            },
            {
                "name": "GI.lesson.defuse_planted_bomb",
                "value": 1
            },
            {
                "name": "GI.lesson.csgo_instr_explain_follow_bomber",
                "value": 1
            },
            {
                "name": "GI.lesson.csgo_instr_explain_pickup_bomb",
                "value": 1
            },
            {
                "name": "GI.lesson.Csgo_cycle_weapons_kb",
                "value": 16
            },
            {
                "name": "GI.lesson.csgo_instr_explain_zoom",
                "value": 16
            },
            {
                "name": "GI.lesson.csgo_instr_explain_reload",
                "value": 17
            },
            {
                "name": "GI.lesson.tr_explain_plant_bomb",
                "value": 16
            },
            {
                "name": "GI.lesson.bomb_sites_B",
                "value": 1
            },
            {
                "name": "GI.lesson.version_number",
                "value": 16
            },
            {
                "name": "GI.lesson.find_planted_bomb",
                "value": 1
            },
            {
                "name": "GI.lesson.csgo_instr_explain_inspect",
                "value": 32
            }
        ]
    }
}