{
    "playerstats": {
        "steamID": "76561198060014438",
        "gameName": "",
        "stats": [
            {
                "name": "deaths",
                "value": 69
            },
            {
                "name": "bullet_fired",
                "value": 1324
            },
            {
                "name": "arrow_fired",
                "value": 356
            },
            {
                "name": "item_drop",
                "value": 889
            },
            {
                "name": "blueprint_studied",
                "value": 103
            },
            {
                "name": "death_fall",
                "value": 10
            },
            {
                "name": "kill_player",
                "value": 33
            },
            {
                "name": "bullet_hit_player",
                "value": 111
            },
            {
                "name": "arrow_hit_entity",
                "value": 74
            },
            {
                "name": "harvest.stones",
                "value": 94750
            },
            {
                "name": "bullet_hit_entity",
                "value": 160
            },
            {
                "name": "harvest.cloth",
                "value": 1835
            },
            {
                "name": "harvest.wood",
                "value": 217744
            },
            {
                "name": "arrow_hit_building",
                "value": 64
            },
            {
                "name": "kill_bear",
                "value": 21
            },
            {
                "name": "kill_boar",
                "value": 19
            },
            {
                "name": "kill_stag",
                "value": 25
            },
            {
                "name": "kill_horse",
                "value": 12
            },
            {
                "name": "kill_wolf",
                "value": 8
            },
            {
                "name": "headshot",
                "value": 69
            },
            {
                "name": "arrow_hit_boar",
                "value": 10
            },
            {
                "name": "arrow_hit_bear",
                "value": 21
            },
            {
                "name": "arrow_hit_wolf",
                "value": 2
            },
            {
                "name": "arrow_hit_stag",
                "value": 23
            },
            {
                "name": "bullet_hit_building",
                "value": 412
            },
            {
                "name": "arrow_hit_horse",
                "value": 9
            },
            {
                "name": "arrow_hit_player",
                "value": 33
            },
            {
                "name": "death_entity",
                "value": 15
            },
            {
                "name": "death_bear",
                "value": 1
            },
            {
                "name": "shotgun_fired",
                "value": 2
            },
            {
                "name": "bullet_hit_bear",
                "value": 61
            },
            {
                "name": "bullet_hit_horse",
                "value": 25
            },
            {
                "name": "bullet_hit_stag",
                "value": 24
            },
            {
                "name": "bullet_hit_wolf",
                "value": 3
            },
            {
                "name": "bullet_hit_boar",
                "value": 6
            },
            {
                "name": "bullet_hit_sign",
                "value": 1
            },
            {
                "name": "wounded",
                "value": 54
            },
            {
                "name": "wounded_assisted",
                "value": 20
            },
            {
                "name": "wounded_healed",
                "value": 17
            },
            {
                "name": "bullet_hit_playercorpse",
                "value": 13
            },
            {
                "name": "bullet_hit_corpse",
                "value": 6
            }
        ]
    }
}