{
    "steamID": "76561198068183603",
    "gameName": "",
    "stats": [
        {
            "name": "deaths",
            "value": 90
        },
        {
            "name": "bullet_fired",
            "value": 11434
        },
        {
            "name": "arrow_fired",
            "value": 830
        },
        {
            "name": "rocket_fired",
            "value": 18
        },
        {
            "name": "item_drop",
            "value": 710
        },
        {
            "name": "blueprint_studied",
            "value": 45
        },
        {
            "name": "death_suicide",
            "value": 17
        },
        {
            "name": "kill_player",
            "value": 137
        },
        {
            "name": "bullet_hit_player",
            "value": 2556
        },
        {
            "name": "arrow_hit_entity",
            "value": 130
        },
        {
            "name": "harvest.stones",
            "value": 32
        },
        {
            "name": "bullet_hit_entity",
            "value": 1286
        },
        {
            "name": "harvest.cloth",
            "value": 69
        },
        {
            "name": "harvest.wood",
            "value": 1385
        },
        {
            "name": "arrow_hit_building",
            "value": 48
        },
        {
            "name": "kill_bear",
            "value": 4
        },
        {
            "name": "kill_boar",
            "value": 44
        },
        {
            "name": "kill_stag",
            "value": 4
        },
        {
            "name": "kill_chicken",
            "value": 5
        },
        {
            "name": "kill_wolf",
            "value": 16
        },
        {
            "name": "headshot",
            "value": 494
        },
        {
            "name": "arrow_hit_boar",
            "value": 112
        },
        {
            "name": "arrow_hit_bear",
            "value": 48
        },
        {
            "name": "arrow_hit_wolf",
            "value": 33
        },
        {
            "name": "arrow_hit_stag",
            "value": 18
        },
        {
            "name": "bullet_hit_building",
            "value": 1085
        },
        {
            "name": "arrow_hit_player",
            "value": 58
        },
        {
            "name": "death_entity",
            "value": 10
        },
        {
            "name": "death_bear",
            "value": 2
        },
        {
            "name": "shotgun_fired",
            "value": 1056
        },
        {
            "name": "shotgun_hit_building",
            "value": 14
        },
        {
            "name": "shotgun_hit_player",
            "value": 106
        },
        {
            "name": "bullet_hit_bear",
            "value": 1
        },
        {
            "name": "shotgun_hit_entity",
            "value": 11
        },
        {
            "name": "bullet_hit_wolf",
            "value": 5
        },
        {
            "name": "bullet_hit_boar",
            "value": 7
        },
        {
            "name": "bullet_hit_sign",
            "value": 3
        },
        {
            "name": "wounded",
            "value": 108
        },
        {
            "name": "wounded_assisted",
            "value": 5
        },
        {
            "name": "wounded_healed",
            "value": 5
        },
        {
            "name": "bullet_hit_playercorpse",
            "value": 42
        },
        {
            "name": "bullet_hit_corpse",
            "value": 1
        },
        {
            "name": "INVENTORY_OPENED",
            "value": 17370
        },
        {
            "name": "CRAFTING_OPENED",
            "value": 938
        },
        {
            "name": "harvested_wood",
            "value": 100
        },
        {
            "name": "harvested_stones",
            "value": 100
        },
        {
            "name": "MAP_OPENED",
            "value": 5924
        },
        {
            "name": "CUPBOARD_OPENED",
            "value": 430
        },
        {
            "name": "ITEM_EXAMINED",
            "value": 5
        },
        {
            "name": "comfort_duration",
            "value": 19607.83203125
        },
        {
            "name": "calories_consumed",
            "value": 51669.34375
        },
        {
            "name": "water_consumed",
            "value": 100879.53125
        },
        {
            "name": "radiation_exposure_duration",
            "value": 22.923828125
        },
        {
            "name": "cold_exposure_duration",
            "value": 36491.16796875
        },
        {
            "name": "hot_exposure_duration",
            "value": 12644.744140625
        },
        {
            "name": "melee_strikes",
            "value": 6822
        },
        {
            "name": "melee_thrown",
            "value": 77
        },
        {
            "name": "arrows_shot",
            "value": 910
        },
        {
            "name": "seconds_speaking",
            "value": 107.32538604736328
        },
        {
            "name": "acquired_lowgradefuel",
            "value": 4855
        },
        {
            "name": "acquired_metal.ore",
            "value": 27559
        },
        {
            "name": "acquired_scrap",
            "value": 3239
        },
        {
            "name": "topology_road_duration",
            "value": 2090
        },
        {
            "name": "destroyed_barrels",
            "value": 280
        },
        {
            "name": "horse_distance_ridden",
            "value": 16345
        },
        {
            "name": "cargoship_bridge_visits",
            "value": 1
        },
        {
            "name": "kill_scientist",
            "value": 12
        },
        {
            "name": "horse_distance_ridden_km",
            "value": 15
        },
        {
            "name": "InstrumentNotesPlayed",
            "value": 1712
        },
        {
            "name": "InstrumentFullKeyboardMode",
            "value": 3
        },
        {
            "name": "InstrumentNotesPlayedBinds",
            "value": 36
        }
    ],
    "achievements": [
        {
            "name": "PLACE_CAMPFIRE",
            "achieved": 1
        },
        {
            "name": "CRAFT_CAMPFIRE",
            "achieved": 1
        },
        {
            "name": "COLLECT_100_WOOD",
            "achieved": 1
        },
        {
            "name": "CRAFT_STONE_HATCHET",
            "achieved": 1
        },
        {
            "name": "COLLECT_200_STONE",
            "achieved": 1
        },
        {
            "name": "CRAFT_STONE_PICKAXE",
            "achieved": 1
        },
        {
            "name": "COLLECT_50_LGF",
            "achieved": 1
        },
        {
            "name": "COLLECT_300_METAL_ORE",
            "achieved": 1
        },
        {
            "name": "VISIT_ROAD",
            "achieved": 1
        },
        {
            "name": "COLLECT_65_SCRAP",
            "achieved": 1
        },
        {
            "name": "DESTROY_10_BARRELS",
            "achieved": 1
        },
        {
            "name": "IM_THE_CAPTAIN_NOW",
            "achieved": 1
        },
        {
            "name": "GIDDY_UP",
            "achieved": 1
        },
        {
            "name": "KILL_SCIENTIST",
            "achieved": 1
        },
        {
            "name": "PLAY_INSTRUMENT",
            "achieved": 1
        }
    ]
}