{
    "playerstats": {
        "steamID": "76561198346126096",
        "gameName": "PAYDAY 2",
        "achievements": [
            {
                "name": "yeah_hes_a_gold_digger",
                "achieved": 1
            },
            {
                "name": "how_do_you_like_me_now",
                "achieved": 1
            },
            {
                "name": "armed_to_the_teeth",
                "achieved": 1
            },
            {
                "name": "would_you_like_your_receipt",
                "achieved": 1
            },
            {
                "name": "fully_loaded",
                "achieved": 1
            },
            {
                "name": "masked_villain",
                "achieved": 1
            },
            {
                "name": "no_one_cared_who_i_was",
                "achieved": 1
            },
            {
                "name": "no_turning_back",
                "achieved": 1
            },
            {
                "name": "spend_money_to_make_money",
                "achieved": 1
            },
            {
                "name": "going_places",
                "achieved": 1
            },
            {
                "name": "you_gotta_start_somewhere",
                "achieved": 1
            },
            {
                "name": "guilty_of_crime",
                "achieved": 1
            },
            {
                "name": "gone_in_30_seconds",
                "achieved": 1
            },
            {
                "name": "armed_and_dangerous",
                "achieved": 1
            },
            {
                "name": "big_shot",
                "achieved": 1
            },
            {
                "name": "gage2_6",
                "achieved": 1
            },
            {
                "name": "gage2_8",
                "achieved": 1
            },
            {
                "name": "death_31",
                "achieved": 1
            },
            {
                "name": "gage4_4",
                "achieved": 1
            },
            {
                "name": "gage4_5",
                "achieved": 1
            },
            {
                "name": "gage4_10",
                "achieved": 1
            },
            {
                "name": "bulldog_1",
                "achieved": 1
            },
            {
                "name": "halloween_nightmare_5",
                "achieved": 1
            },
            {
                "name": "ameno_8",
                "achieved": 1
            },
            {
                "name": "fort_3",
                "achieved": 1
            },
            {
                "name": "fort_2",
                "achieved": 1
            },
            {
                "name": "grill_1",
                "achieved": 1
            },
            {
                "name": "grill_4",
                "achieved": 1
            },
            {
                "name": "brooklyn_1",
                "achieved": 1
            },
            {
                "name": "brooklyn_3",
                "achieved": 1
            },
            {
                "name": "pick_666",
                "achieved": 1
            },
            {
                "name": "pick_41",
                "achieved": 1
            },
            {
                "name": "cee_1",
                "achieved": 1
            },
            {
                "name": "cee_2",
                "achieved": 1
            },
            {
                "name": "wwh_1",
                "achieved": 1
            },
            {
                "name": "wwh_2",
                "achieved": 1
            },
            {
                "name": "wwh_3",
                "achieved": 1
            },
            {
                "name": "wwh_4",
                "achieved": 1
            },
            {
                "name": "wwh_5",
                "achieved": 1
            },
            {
                "name": "trk_af_0",
                "achieved": 1
            },
            {
                "name": "trk_af_1",
                "achieved": 1
            },
            {
                "name": "trk_af_2",
                "achieved": 1
            },
            {
                "name": "trk_nc_0",
                "achieved": 1
            },
            {
                "name": "trk_sx_0",
                "achieved": 1
            },
            {
                "name": "trk_sx_1",
                "achieved": 1
            },
            {
                "name": "trk_sx_2",
                "achieved": 1
            },
            {
                "name": "trk_fw_0",
                "achieved": 1
            },
            {
                "name": "trk_sh_0",
                "achieved": 1
            },
            {
                "name": "trk_sh_1",
                "achieved": 1
            },
            {
                "name": "trk_hb_1",
                "achieved": 1
            },
            {
                "name": "trk_hb_2",
                "achieved": 1
            },
            {
                "name": "trk_hb_3",
                "achieved": 1
            },
            {
                "name": "trk_sa_0",
                "achieved": 1
            },
            {
                "name": "trk_sa_1",
                "achieved": 1
            },
            {
                "name": "trk_sa_2",
                "achieved": 1
            },
            {
                "name": "trk_sa_3",
                "achieved": 1
            },
            {
                "name": "trk_sa_4",
                "achieved": 1
            },
            {
                "name": "trk_cs_0",
                "achieved": 1
            },
            {
                "name": "trk_cs_1",
                "achieved": 1
            },
            {
                "name": "trk_cs_2",
                "achieved": 1
            },
            {
                "name": "trk_cs_3",
                "achieved": 1
            },
            {
                "name": "nbm_1",
                "achieved": 1
            },
            {
                "name": "nbm_2",
                "achieved": 1
            },
            {
                "name": "nbm_3",
                "achieved": 1
            },
            {
                "name": "nbm_4",
                "achieved": 1
            },
            {
                "name": "cac_4",
                "achieved": 1
            },
            {
                "name": "cac_10",
                "achieved": 1
            },
            {
                "name": "cac_28",
                "achieved": 1
            },
            {
                "name": "uno_4",
                "achieved": 1
            },
            {
                "name": "skm_29",
                "achieved": 1
            }
        ],
        "stats": [
            {
                "name": "player_time_0h",
                "value": 0
            },
            {
                "name": "player_time_10h",
                "value": 0
            },
            {
                "name": "player_time_20h",
                "value": 1
            },
            {
                "name": "player_level",
                "value": 86
            },
            {
                "name": "player_level_0",
                "value": 0
            },
            {
                "name": "player_level_10",
                "value": 0
            },
            {
                "name": "player_level_30",
                "value": 0
            },
            {
                "name": "player_level_40",
                "value": 0
            },
            {
                "name": "player_level_50",
                "value": 0
            },
            {
                "name": "player_level_60",
                "value": 0
            },
            {
                "name": "player_level_70",
                "value": 0
            },
            {
                "name": "player_level_80",
                "value": 1
            },
            {
                "name": "player_cash_0k",
                "value": 0
            },
            {
                "name": "player_cash_100k",
                "value": 0
            },
            {
                "name": "player_cash_1000k",
                "value": 0
            },
            {
                "name": "player_cash_10000k",
                "value": 1
            },
            {
                "name": "heist_failed",
                "value": 18
            },
            {
                "name": "heist_success",
                "value": 47
            },
            {
                "name": "skill_mastermind",
                "value": 0
            },
            {
                "name": "skill_mastermind_0",
                "value": 1
            },
            {
                "name": "skill_mastermind_5",
                "value": 0
            },
            {
                "name": "skill_enforcer",
                "value": 3
            },
            {
                "name": "skill_enforcer_0",
                "value": 0
            },
            {
                "name": "skill_enforcer_5",
                "value": 1
            },
            {
                "name": "skill_enforcer_10",
                "value": 0
            },
            {
                "name": "skill_technician",
                "value": 0
            },
            {
                "name": "skill_technician_0",
                "value": 1
            },
            {
                "name": "skill_technician_5",
                "value": 0
            },
            {
                "name": "skill_ghost",
                "value": 1
            },
            {
                "name": "skill_ghost_0",
                "value": 0
            },
            {
                "name": "skill_ghost_5",
                "value": 1
            },
            {
                "name": "skill_ghost_10",
                "value": 0
            },
            {
                "name": "skill_ghost_15",
                "value": 0
            },
            {
                "name": "skill_mastermind_cable_guy",
                "value": 0
            },
            {
                "name": "skill_mastermind_combat_medic",
                "value": 0
            },
            {
                "name": "skill_mastermind_combat_medic_ace",
                "value": 0
            },
            {
                "name": "skill_mastermind_triathlete",
                "value": 0
            },
            {
                "name": "skill_mastermind_fast_learner",
                "value": 0
            },
            {
                "name": "skill_mastermind_fast_learner_ace",
                "value": 0
            },
            {
                "name": "skill_mastermind_medic_2x",
                "value": 0
            },
            {
                "name": "skill_mastermind_medic_2x_ace",
                "value": 0
            },
            {
                "name": "skill_mastermind_joker",
                "value": 0
            },
            {
                "name": "skill_mastermind_inspire",
                "value": 0
            },
            {
                "name": "skill_mastermind_inspire_ace",
                "value": 0
            },
            {
                "name": "skill_enforcer_oppressor",
                "value": 1
            },
            {
                "name": "skill_enforcer_oppressor_ace",
                "value": 1
            },
            {
                "name": "skill_enforcer_ammo_reservoir",
                "value": 0
            },
            {
                "name": "skill_enforcer_ammo_reservoir_ace",
                "value": 0
            },
            {
                "name": "skill_enforcer_pack_mule",
                "value": 0
            },
            {
                "name": "skill_enforcer_show_of_force",
                "value": 0
            },
            {
                "name": "skill_enforcer_show_of_force_ace",
                "value": 0
            },
            {
                "name": "skill_enforcer_underdog",
                "value": 1
            },
            {
                "name": "skill_enforcer_underdog_ace",
                "value": 0
            },
            {
                "name": "skill_enforcer_shotgun_impact",
                "value": 1
            },
            {
                "name": "skill_enforcer_shotgun_impact_ace",
                "value": 1
            },
            {
                "name": "skill_enforcer_shotgun_cqb",
                "value": 1
            },
            {
                "name": "skill_enforcer_shotgun_cqb_ace",
                "value": 1
            },
            {
                "name": "skill_enforcer_ammo_2x",
                "value": 1
            },
            {
                "name": "skill_enforcer_ammo_2x_ace",
                "value": 0
            },
            {
                "name": "skill_enforcer_bandoliers",
                "value": 0
            },
            {
                "name": "skill_enforcer_portable_saw",
                "value": 0
            },
            {
                "name": "skill_enforcer_overkill",
                "value": 1
            },
            {
                "name": "skill_enforcer_overkill_ace",
                "value": 0
            },
            {
                "name": "skill_ghost_scavenger",
                "value": 1
            },
            {
                "name": "skill_ghost_scavenger_ace",
                "value": 0
            },
            {
                "name": "skill_ghost_sprinter",
                "value": 1
            },
            {
                "name": "skill_ghost_sprinter_ace",
                "value": 0
            },
            {
                "name": "skill_ghost_chameleon",
                "value": 0
            },
            {
                "name": "skill_ghost_chameleon_ace",
                "value": 0
            },
            {
                "name": "skill_ghost_cleaner",
                "value": 0
            },
            {
                "name": "skill_ghost_cleaner_ace",
                "value": 0
            },
            {
                "name": "skill_ghost_ecm_2x",
                "value": 0
            },
            {
                "name": "skill_ghost_hitman",
                "value": 0
            },
            {
                "name": "skill_ghost_hitman_ace",
                "value": 0
            },
            {
                "name": "skill_ghost_silence_expert",
                "value": 0
            },
            {
                "name": "skill_ghost_silence_expert_ace",
                "value": 0
            },
            {
                "name": "weapon_used_new_m4",
                "value": 12
            },
            {
                "name": "weapon_used_amcar",
                "value": 1
            },
            {
                "name": "weapon_used_saiga",
                "value": 1
            },
            {
                "name": "weapon_used_glock_17",
                "value": 3
            },
            {
                "name": "weapon_used_new_raging_bull",
                "value": 11
            },
            {
                "name": "gadget_used_ammo_bag",
                "value": 46
            },
            {
                "name": "gadget_used_doctor_bag",
                "value": 5
            },
            {
                "name": "gadget_used_ecm_jammer",
                "value": 3
            },
            {
                "name": "mask_used_character_locked",
                "value": 3
            },
            {
                "name": "difficulty_normal",
                "value": 5
            },
            {
                "name": "difficulty_hard",
                "value": 5
            },
            {
                "name": "difficulty_overkill",
                "value": 10
            },
            {
                "name": "difficulty_overkill_145",
                "value": 43
            },
            {
                "name": "halloween_5_stats",
                "value": 15
            },
            {
                "name": "level_four_stores",
                "value": 1
            },
            {
                "name": "level_nightclub",
                "value": 2
            },
            {
                "name": "level_framing_frame_1",
                "value": 1
            },
            {
                "name": "level_framing_frame_2",
                "value": 1
            },
            {
                "name": "level_firestarter_1",
                "value": 3
            },
            {
                "name": "level_firestarter_2",
                "value": 1
            },
            {
                "name": "level_escape_park",
                "value": 1
            },
            {
                "name": "level_escape_overpass",
                "value": 1
            },
            {
                "name": "level_arm_cro",
                "value": 2
            },
            {
                "name": "level_arm_und",
                "value": 1
            },
            {
                "name": "level_branchbank",
                "value": 1
            },
            {
                "name": "job_four_stores",
                "value": 1
            },
            {
                "name": "job_nightclub",
                "value": 16
            },
            {
                "name": "job_mallcrasher",
                "value": 1
            },
            {
                "name": "job_branchbank_gold_prof",
                "value": 1
            },
            {
                "name": "job_framing_frame",
                "value": 8
            },
            {
                "name": "job_arm_hcm",
                "value": 1
            },
            {
                "name": "mask_used_frank",
                "value": 8
            },
            {
                "name": "gage_9_stats",
                "value": 52
            },
            {
                "name": "level_roberts",
                "value": 2
            },
            {
                "name": "job_roberts",
                "value": 1
            },
            {
                "name": "difficulty_overkill_290",
                "value": 1
            },
            {
                "name": "player_rank_0",
                "value": 1
            },
            {
                "name": "level_kosugi",
                "value": 1
            },
            {
                "name": "job_kosugi",
                "value": 17
            },
            {
                "name": "mask_used_surprise",
                "value": 5
            },
            {
                "name": "gage4_10_stats",
                "value": 205
            },
            {
                "name": "melee_used_weapon",
                "value": 7
            },
            {
                "name": "armor_used_level_1",
                "value": 7
            },
            {
                "name": "armor_used_level_2",
                "value": 4
            },
            {
                "name": "armor_used_level_3",
                "value": 7
            },
            {
                "name": "armor_used_level_4",
                "value": 1
            },
            {
                "name": "armor_used_level_6",
                "value": 53
            },
            {
                "name": "weapon_kills_amcar",
                "value": 4
            },
            {
                "name": "weapon_kills_glock_17",
                "value": 77
            },
            {
                "name": "weapon_kills_new_m4",
                "value": 447
            },
            {
                "name": "weapon_kills_new_raging_bull",
                "value": 336
            },
            {
                "name": "weapon_kills_p90",
                "value": 1
            },
            {
                "name": "weapon_kills_saiga",
                "value": 10
            },
            {
                "name": "enemy_kills_cop",
                "value": 63
            },
            {
                "name": "enemy_kills_fbi",
                "value": 16
            },
            {
                "name": "enemy_kills_fbi_swat",
                "value": 1491
            },
            {
                "name": "enemy_kills_fbi_heavy_swat",
                "value": 1633
            },
            {
                "name": "enemy_kills_swat",
                "value": 311
            },
            {
                "name": "enemy_kills_heavy_swat",
                "value": 210
            },
            {
                "name": "enemy_kills_city_swat",
                "value": 337
            },
            {
                "name": "enemy_kills_security",
                "value": 131
            },
            {
                "name": "enemy_kills_gensec",
                "value": 2
            },
            {
                "name": "enemy_kills_gangster",
                "value": 19
            },
            {
                "name": "enemy_kills_sniper",
                "value": 74
            },
            {
                "name": "enemy_kills_shield",
                "value": 197
            },
            {
                "name": "enemy_kills_spooc",
                "value": 80
            },
            {
                "name": "enemy_kills_taser",
                "value": 308
            },
            {
                "name": "contract_four_stores_win_dropin",
                "value": 1
            },
            {
                "name": "contract_nightclub_win",
                "value": 1
            },
            {
                "name": "contract_nightclub_win_dropin",
                "value": 1
            },
            {
                "name": "contract_roberts_fail",
                "value": 1
            },
            {
                "name": "contract_kosugi_fail",
                "value": 1
            },
            {
                "name": "weapon_used_judge",
                "value": 42
            },
            {
                "name": "weapon_kills_judge",
                "value": 2106
            },
            {
                "name": "stat_version",
                "value": 2
            },
            {
                "name": "enemy_kills_mobster",
                "value": 20
            },
            {
                "name": "level_mia_1",
                "value": 3
            },
            {
                "name": "character_used_russian",
                "value": 1
            },
            {
                "name": "character_used_spanish",
                "value": 1
            },
            {
                "name": "character_used_american",
                "value": 7
            },
            {
                "name": "level_watchdogs_1_night",
                "value": 1
            },
            {
                "name": "level_welcome_to_the_jungle_1_night",
                "value": 1
            },
            {
                "name": "level_hox_1",
                "value": 2
            },
            {
                "name": "level_hox_2",
                "value": 3
            },
            {
                "name": "job_hox",
                "value": 2
            },
            {
                "name": "contract_hox_win",
                "value": 1
            },
            {
                "name": "enemy_kills_civilian",
                "value": 56
            },
            {
                "name": "enemy_kills_civilian_female",
                "value": 24
            },
            {
                "name": "level_haunted",
                "value": 1
            },
            {
                "name": "job_haunted",
                "value": 1
            },
            {
                "name": "contract_haunted_win",
                "value": 1
            },
            {
                "name": "enemy_kills_tank_hw",
                "value": 4
            },
            {
                "name": "skill_hoxton",
                "value": 0
            },
            {
                "name": "skill_hoxton_0",
                "value": 1
            },
            {
                "name": "skill_hoxton_5",
                "value": 0
            },
            {
                "name": "skill_hoxton_perseverance",
                "value": 1
            },
            {
                "name": "skill_hoxton_perseverance_ace",
                "value": 1
            },
            {
                "name": "skill_hoxton_trigger_happy",
                "value": 0
            },
            {
                "name": "skill_hoxton_trigger_happy_ace",
                "value": 0
            },
            {
                "name": "skill_hoxton_akimbo",
                "value": 1
            },
            {
                "name": "skill_hoxton_akimbo_ace",
                "value": 1
            },
            {
                "name": "gadget_used_first_aid",
                "value": 1
            },
            {
                "name": "gadget_used_body_bag",
                "value": 8
            },
            {
                "name": "option_decide_host",
                "value": 7
            },
            {
                "name": "info_playing_win_host",
                "value": 7
            },
            {
                "name": "info_playing_win_client",
                "value": 35
            },
            {
                "name": "info_playing_win_client_dropin",
                "value": 5
            },
            {
                "name": "info_playing_fail_host",
                "value": 2
            },
            {
                "name": "info_playing_fail_client",
                "value": 16
            },
            {
                "name": "contract_watchdogs_night_fail",
                "value": 1
            },
            {
                "name": "job_watchdogs_night",
                "value": 1
            },
            {
                "name": "job_welcome_to_the_jungle_night_prof",
                "value": 8
            },
            {
                "name": "melee_used_boxing_gloves",
                "value": 2
            },
            {
                "name": "melee_kills_boxing_gloves",
                "value": 2
            },
            {
                "name": "ameno_08_stats",
                "value": 432
            },
            {
                "name": "level_rat",
                "value": 2
            },
            {
                "name": "level_cage",
                "value": 3
            },
            {
                "name": "job_cage",
                "value": 50
            },
            {
                "name": "contract_cage_win",
                "value": 2
            },
            {
                "name": "contract_cage_fail",
                "value": 1
            },
            {
                "name": "player_specialization_4",
                "value": 9
            },
            {
                "name": "specialization_used_1",
                "value": 6
            },
            {
                "name": "specialization_used_4",
                "value": 66
            },
            {
                "name": "mask_used_speedrunner",
                "value": 12
            },
            {
                "name": "player_specialization_active",
                "value": 4
            },
            {
                "name": "grenade_used_frag",
                "value": 2
            },
            {
                "name": "grenade_used_wpn_prj_ace",
                "value": 15
            },
            {
                "name": "grenade_kills_wpn_prj_ace",
                "value": 20
            },
            {
                "name": "option_resolution_1920x1080",
                "value": 0
            },
            {
                "name": "option_resolution_1280x720",
                "value": 1
            },
            {
                "name": "equipped_mask",
                "value": 237
            },
            {
                "name": "equipped_primary",
                "value": 162
            },
            {
                "name": "equipped_secondary",
                "value": 59
            },
            {
                "name": "equipped_melee",
                "value": 92
            },
            {
                "name": "equipped_grenade",
                "value": 5
            },
            {
                "name": "equipped_armor",
                "value": 6
            },
            {
                "name": "equipped_character",
                "value": 19
            },
            {
                "name": "equipped_deployable",
                "value": 1
            },
            {
                "name": "enemy_kills_tank_green",
                "value": 111
            },
            {
                "name": "enemy_kills_tank_black",
                "value": 110
            },
            {
                "name": "enemy_kills_tank_skull",
                "value": 3
            },
            {
                "name": "weapon_shots_amcar",
                "value": 114
            },
            {
                "name": "weapon_shots_glock_17",
                "value": 181
            },
            {
                "name": "weapon_shots_new_m4",
                "value": 1734
            },
            {
                "name": "weapon_shots_new_raging_bull",
                "value": 1058
            },
            {
                "name": "weapon_shots_saiga",
                "value": 57
            },
            {
                "name": "weapon_shots_judge",
                "value": 4705
            },
            {
                "name": "weapon_hits_amcar",
                "value": 30
            },
            {
                "name": "weapon_hits_glock_17",
                "value": 55
            },
            {
                "name": "weapon_hits_new_m4",
                "value": 379
            },
            {
                "name": "weapon_hits_new_raging_bull",
                "value": 367
            },
            {
                "name": "weapon_hits_saiga",
                "value": 58
            },
            {
                "name": "weapon_hits_judge",
                "value": 3824
            },
            {
                "name": "enemy_kills_hostage_rescue",
                "value": 1
            },
            {
                "name": "enemy_kills_murkywater",
                "value": 65
            },
            {
                "name": "enemy_kills_phalanx_minion",
                "value": 2
            },
            {
                "name": "level_jolly",
                "value": 2
            },
            {
                "name": "level_red2",
                "value": 3
            },
            {
                "name": "level_dinner",
                "value": 2
            },
            {
                "name": "level_nail",
                "value": 1
            },
            {
                "name": "level_pbr2",
                "value": 1
            },
            {
                "name": "job_jolly",
                "value": 4
            },
            {
                "name": "job_red2",
                "value": 4
            },
            {
                "name": "job_dinner",
                "value": 1
            },
            {
                "name": "contract_jolly_win",
                "value": 2
            },
            {
                "name": "contract_red2_win",
                "value": 1
            },
            {
                "name": "contract_red2_win_dropin",
                "value": 1
            },
            {
                "name": "contract_dinner_win",
                "value": 1
            },
            {
                "name": "melee_used_boxcutter",
                "value": 3
            },
            {
                "name": "mask_used_tiara",
                "value": 1
            },
            {
                "name": "enemy_kills_biker",
                "value": 5
            },
            {
                "name": "level_cane",
                "value": 1
            },
            {
                "name": "job_peta",
                "value": 3
            },
            {
                "name": "level_pal",
                "value": 1
            },
            {
                "name": "level_man",
                "value": 3
            },
            {
                "name": "melee_used_ballistic",
                "value": 4
            },
            {
                "name": "character_used_jimmy",
                "value": 3
            },
            {
                "name": "melee_kills_ballistic",
                "value": 5
            },
            {
                "name": "job_dark",
                "value": 6
            },
            {
                "name": "melee_kills_zeus",
                "value": 1
            },
            {
                "name": "info_playing_pc",
                "value": 1
            },
            {
                "name": "grenade_used_frag_com",
                "value": 5
            },
            {
                "name": "skill_mastermind_tea_time",
                "value": 0
            },
            {
                "name": "skill_mastermind_tea_time_ace",
                "value": 0
            },
            {
                "name": "skill_mastermind_stable_shot",
                "value": 0
            },
            {
                "name": "skill_mastermind_stable_shot_ace",
                "value": 0
            },
            {
                "name": "skill_mastermind_rifleman",
                "value": 0
            },
            {
                "name": "skill_mastermind_rifleman_ace",
                "value": 0
            },
            {
                "name": "skill_mastermind_sharpshooter",
                "value": 0
            },
            {
                "name": "skill_mastermind_sharpshooter_ace",
                "value": 0
            },
            {
                "name": "skill_enforcer_close_by",
                "value": 1
            },
            {
                "name": "skill_enforcer_close_by_ace",
                "value": 1
            },
            {
                "name": "skill_enforcer_iron_man",
                "value": 1
            },
            {
                "name": "skill_enforcer_iron_man_ace",
                "value": 1
            },
            {
                "name": "skill_enforcer_prison_wife",
                "value": 0
            },
            {
                "name": "skill_enforcer_prison_wife_ace",
                "value": 0
            },
            {
                "name": "skill_enforcer_scavenging",
                "value": 1
            },
            {
                "name": "skill_enforcer_scavenging_ace",
                "value": 1
            },
            {
                "name": "skill_technician_defense_up",
                "value": 1
            },
            {
                "name": "skill_technician_eco_sentry",
                "value": 1
            },
            {
                "name": "skill_technician_eco_sentry_ace",
                "value": 0
            },
            {
                "name": "skill_technician_jack_of_all_trades",
                "value": 1
            },
            {
                "name": "skill_technician_jack_of_all_trades_ace",
                "value": 1
            },
            {
                "name": "skill_technician_steady_grip",
                "value": 0
            },
            {
                "name": "skill_technician_steady_grip_ace",
                "value": 0
            },
            {
                "name": "skill_technician_heavy_impact",
                "value": 0
            },
            {
                "name": "skill_technician_shock_and_awe",
                "value": 0
            },
            {
                "name": "skill_ghost_jail_workout",
                "value": 0
            },
            {
                "name": "skill_ghost_jail_workout_ace",
                "value": 0
            },
            {
                "name": "skill_ghost_second_chances",
                "value": 0
            },
            {
                "name": "skill_ghost_second_chances_ace",
                "value": 0
            },
            {
                "name": "skill_ghost_awareness",
                "value": 0
            },
            {
                "name": "skill_ghost_awareness_ace",
                "value": 0
            },
            {
                "name": "skill_ghost_thick_skin",
                "value": 0
            },
            {
                "name": "skill_ghost_thick_skin_ace",
                "value": 0
            },
            {
                "name": "skill_ghost_dire_need",
                "value": 0
            },
            {
                "name": "skill_ghost_optic_illusions",
                "value": 0
            },
            {
                "name": "skill_ghost_optic_illusions_ace",
                "value": 0
            },
            {
                "name": "skill_ghost_backstab",
                "value": 0
            },
            {
                "name": "skill_ghost_backstab_ace",
                "value": 0
            },
            {
                "name": "skill_ghost_unseen_strike",
                "value": 0
            },
            {
                "name": "skill_ghost_unseen_strike_ace",
                "value": 0
            },
            {
                "name": "skill_hoxton_equilibrium",
                "value": 1
            },
            {
                "name": "skill_hoxton_equilibrium_ace",
                "value": 0
            },
            {
                "name": "skill_hoxton_dance_instructor",
                "value": 0
            },
            {
                "name": "skill_hoxton_dance_instructor_ace",
                "value": 0
            },
            {
                "name": "skill_hoxton_gun_fighter",
                "value": 0
            },
            {
                "name": "skill_hoxton_gun_fighter_ace",
                "value": 0
            },
            {
                "name": "skill_hoxton_expert_handling",
                "value": 0
            },
            {
                "name": "skill_hoxton_expert_handling_ace",
                "value": 0
            },
            {
                "name": "skill_hoxton_nine_lives",
                "value": 1
            },
            {
                "name": "skill_hoxton_nine_lives_ace",
                "value": 1
            },
            {
                "name": "skill_hoxton_running_from_death",
                "value": 0
            },
            {
                "name": "skill_hoxton_running_from_death_ace",
                "value": 0
            },
            {
                "name": "skill_hoxton_up_you_go",
                "value": 0
            },
            {
                "name": "skill_hoxton_up_you_go_ace",
                "value": 0
            },
            {
                "name": "skill_hoxton_feign_death",
                "value": 1
            },
            {
                "name": "skill_hoxton_feign_death_ace",
                "value": 1
            },
            {
                "name": "skill_hoxton_messiah",
                "value": 1
            },
            {
                "name": "skill_hoxton_messiah_ace",
                "value": 1
            },
            {
                "name": "skill_hoxton_martial_arts",
                "value": 0
            },
            {
                "name": "info_playing_tutorial_yes",
                "value": 1
            },
            {
                "name": "enemy_kills_cop_female",
                "value": 1
            },
            {
                "name": "difficulty_easy_wish",
                "value": 6
            },
            {
                "name": "difficulty_sm_wish",
                "value": 2
            },
            {
                "name": "level_chill_combat",
                "value": 6
            },
            {
                "name": "job_chill",
                "value": 1
            },
            {
                "name": "job_chill_combat",
                "value": 8
            },
            {
                "name": "contract_chill_combat_win",
                "value": 4
            },
            {
                "name": "contract_chill_combat_win_dropin",
                "value": 1
            },
            {
                "name": "contract_chill_combat_fail",
                "value": 1
            },
            {
                "name": "grenade_used_concussion",
                "value": 10
            },
            {
                "name": "enemy_kills_medic",
                "value": 318
            },
            {
                "name": "enemy_kills_security_undominatable",
                "value": 1
            },
            {
                "name": "level_help",
                "value": 1
            },
            {
                "name": "level_moon",
                "value": 1
            },
            {
                "name": "job_moon",
                "value": 2
            },
            {
                "name": "contract_moon_win",
                "value": 1
            },
            {
                "name": "player_coins",
                "value": 111
            },
            {
                "name": "player_coins_0",
                "value": 0
            },
            {
                "name": "player_coins_24",
                "value": 0
            },
            {
                "name": "player_coins_48",
                "value": 0
            },
            {
                "name": "player_coins_72",
                "value": 0
            },
            {
                "name": "player_coins_96",
                "value": 1
            },
            {
                "name": "character_used_chico",
                "value": 1
            },
            {
                "name": "mask_used_sha_01",
                "value": 2
            },
            {
                "name": "melee_used_ostry",
                "value": 1
            },
            {
                "name": "job_fish",
                "value": 17
            },
            {
                "name": "level_fish",
                "value": 3
            },
            {
                "name": "contract_fish_fail",
                "value": 3
            },
            {
                "name": "level_run",
                "value": 1
            },
            {
                "name": "grenade_used_fir_com",
                "value": 40
            },
            {
                "name": "grenade_kills_fir_com",
                "value": 279
            },
            {
                "name": "level_glace",
                "value": 3
            },
            {
                "name": "melee_used_agave",
                "value": 45
            },
            {
                "name": "character_used_max",
                "value": 24
            },
            {
                "name": "melee_kills_agave",
                "value": 10
            },
            {
                "name": "eng_4_stats",
                "value": 1
            },
            {
                "name": "melee_used_push",
                "value": 3
            },
            {
                "name": "melee_kills_push",
                "value": 1
            },
            {
                "name": "mask_used_cmo_03",
                "value": 1
            },
            {
                "name": "weapon_hits_basset",
                "value": 355
            },
            {
                "name": "contract_wwh_win",
                "value": 1
            },
            {
                "name": "job_wwh",
                "value": 2
            },
            {
                "name": "level_wwh",
                "value": 1
            },
            {
                "name": "weapon_used_basset",
                "value": 2
            },
            {
                "name": "player_specialization_19",
                "value": 4
            },
            {
                "name": "weapon_kills_basset",
                "value": 19
            },
            {
                "name": "weapon_shots_basset",
                "value": 388
            },
            {
                "name": "level_rvd2",
                "value": 1
            },
            {
                "name": "melee_used_clean",
                "value": 2
            },
            {
                "name": "melee_kills_clean",
                "value": 1
            },
            {
                "name": "level_brb",
                "value": 1
            },
            {
                "name": "cac_3_stats",
                "value": 3
            },
            {
                "name": "cac_7_stats",
                "value": 70800000
            },
            {
                "name": "cac_34_stats",
                "value": 20
            },
            {
                "name": "cac_35_stats",
                "value": 4
            },
            {
                "name": "job_des",
                "value": 3
            },
            {
                "name": "mask_used_toon_01",
                "value": 5
            },
            {
                "name": "weapon_used_x_2006m",
                "value": 6
            },
            {
                "name": "weapon_used_x_judge",
                "value": 42
            },
            {
                "name": "weapon_kills_x_2006m",
                "value": 220
            },
            {
                "name": "weapon_kills_x_judge",
                "value": 1940
            },
            {
                "name": "weapon_shots_x_2006m",
                "value": 1513
            },
            {
                "name": "weapon_shots_x_judge",
                "value": 10519
            },
            {
                "name": "weapon_hits_x_2006m",
                "value": 495
            },
            {
                "name": "weapon_hits_x_judge",
                "value": 7461
            },
            {
                "name": "level_skm_mus",
                "value": 2
            },
            {
                "name": "job_skm_mus",
                "value": 2
            },
            {
                "name": "contract_skm_mus_win",
                "value": 1
            },
            {
                "name": "contract_skm_mus_fail",
                "value": 1
            },
            {
                "name": "melee_used_fear",
                "value": 3
            },
            {
                "name": "melee_used_happy",
                "value": 1
            },
            {
                "name": "melee_used_hauteur",
                "value": 1
            },
            {
                "name": "mask_used_joy",
                "value": 17
            },
            {
                "name": "mask_used_joy_begins",
                "value": 18
            },
            {
                "name": "character_used_joy",
                "value": 35
            },
            {
                "name": "melee_kills_fear",
                "value": 5
            },
            {
                "name": "suit_used_jail_pd2_clan",
                "value": 47
            },
            {
                "name": "equipped_suit",
                "value": 2
            },
            {
                "name": "suit_used_none",
                "value": 2
            },
            {
                "name": "suit_used_xmas_tuxedo_black",
                "value": 2
            },
            {
                "name": "weapon_color_used_color_tan_khaki",
                "value": 2
            },
            {
                "name": "suit_used_xmas_tuxedo_default",
                "value": 6
            },
            {
                "name": "level_skm_bex",
                "value": 1
            },
            {
                "name": "job_skm_bex",
                "value": 1
            },
            {
                "name": "contract_skm_arena_fail",
                "value": 2
            },
            {
                "name": "contract_skm_bex_fail",
                "value": 1
            },
            {
                "name": "level_skm_arena",
                "value": 2
            },
            {
                "name": "gloves_used_heist_default",
                "value": 36
            },
            {
                "name": "equipped_glove_id",
                "value": 2
            },
            {
                "name": "job_skm_arena",
                "value": 2
            },
            {
                "name": "suit_used_continental",
                "value": 14
            },
            {
                "name": "gloves_used_default",
                "value": 18
            },
            {
                "name": "gloves_used_continental",
                "value": 18
            },
            {
                "name": "weapon_color_used_color_anv_01",
                "value": 33
            },
            {
                "name": "weapon_color_used_color_fex_02",
                "value": 2
            },
            {
                "name": "setting_roman_rank_on",
                "value": 1
            },
            {
                "name": "setting_roman_card_on",
                "value": 1
            },
            {
                "name": "weapon_color_used_color_xm20_01",
                "value": 1
            },
            {
                "name": "weapon_color_used_color_faco_00",
                "value": 24
            },
            {
                "name": "suit_used_thug_default",
                "value": 1
            },
            {
                "name": "weapon_color_used_color_mar21_01",
                "value": 15
            },
            {
                "name": "gsu_stat",
                "value": 6
            },
            {
                "name": "main_menu_crimenet",
                "value": 1
            },
            {
                "name": "main_menu_crimenet_offline",
                "value": 238
            },
            {
                "name": "main_menu_story_missions",
                "value": 51
            },
            {
                "name": "main_menu_inventory",
                "value": 34
            },
            {
                "name": "main_menu_gamehub",
                "value": 1
            },
            {
                "name": "main_menu_quit",
                "value": 52
            },
            {
                "name": "main_menu_options",
                "value": 8
            },
            {
                "name": "main_menu_achievements",
                "value": 115
            },
            {
                "name": "main_menu_fbi_files",
                "value": 74
            }
        ]
    }
}